{
  "MODELS": [
    {
      "id": "the_vault:gear/sword/hotdog_bat",
      "displayName": "Hot Dog Bat",
      "discoverOnRoll": true,
      "allowTransmogrification": true
    },
    {
      "id": "the_vault:gear/sword/crystal",
      "displayName": "Hyper Crystal Sword",
      "discoverOnRoll": true,
      "allowTransmogrification": true
    },
    {
      "id": "the_vault:gear/sword/dogfall",
      "displayName": "Dogfall",
      "discoverOnRoll": true,
      "allowTransmogrification": true
    },
    {
      "id": "the_vault:gear/sword/sword_what",
      "displayName": "No Idea Sword",
      "discoverOnRoll": true,
      "allowTransmogrification": true
    }
  ]
}